{"name":"Prezentacje","tagline":"Grzegorz Wodniczak","body":"# Lista dostępnych prezentacji:\r\n### * Roslyn - rozszerzanie możliwości kompilatora C\\#\r\nPrezentacja na temat analizatorów kodu źródłowego, które rozszerzają możliwości nowej wersji kompilatora języka C# - **Roslyn**.\r\n\r\nAktualna wersja dostępna jest pod [tym adresem](https://github.com/vebaspect/prezentacje/blob/master/Roslyn%20-%20rozszerzanie%20mo%C5%BCliwo%C5%9Bci%20kompilatora%20C%23.pdf).\r\n\r\n### * Less - sposób na uproszczenie pracy z CSS\r\nPrezentacja na temat najpopularniejszego obecnie pre-procesora dla CSS - **Less**.\r\n\r\nAktualna wersja dostępna jest pod [tym adresem](https://github.com/vebaspect/prezentacje/blob/master/Less%20-%20spos%C3%B3b%20na%20uproszczenie%20pracy%20z%20CSS.pdf).","google":"","note":"Don't delete this file! It's used internally to help with page regeneration."}